declare/__init__.py
declare/_declare.py
declare/py.typed
declare-1.0.1.dist-info/LICENSE
declare-1.0.1.dist-info/METADATA
declare-1.0.1.dist-info/WHEEL
declare-1.0.1.dist-info/RECORD
